MANIFEST.in
README.md
notebook_requirements.txt
requirements.txt
setup.cfg
setup.py
stats_requirements.txt
splicemachine/__init__.py
splicemachine/notebook.py
splicemachine/stats.py
splicemachine.egg-info/PKG-INFO
splicemachine.egg-info/SOURCES.txt
splicemachine.egg-info/dependency_links.txt
splicemachine.egg-info/requires.txt
splicemachine.egg-info/top_level.txt
splicemachine/features/__init__.py
splicemachine/features/constants.py
splicemachine/features/feature.py
splicemachine/features/feature_set.py
splicemachine/features/feature_store.py
splicemachine/features/pipe.py
splicemachine/features/pipeline.py
splicemachine/features/training_set.py
splicemachine/features/training_view.py
splicemachine/features/pipelines/__init__.py
splicemachine/features/pipelines/feature_aggregation.py
splicemachine/features/pipelines/utils.py
splicemachine/features/utils/__init__.py
splicemachine/features/utils/drift_utils.py
splicemachine/features/utils/feature_utils.py
splicemachine/features/utils/http_utils.py
splicemachine/features/utils/search_utils.py
splicemachine/features/utils/training_utils.py
splicemachine/mlflow_support/__init__.py
splicemachine/mlflow_support/constants.py
splicemachine/mlflow_support/mlflow_support.py
splicemachine/mlflow_support/utilities.py
splicemachine/mlflow_support/flavors/__init__.py
splicemachine/mlflow_support/flavors/mlflow_fastai.py
splicemachine/mlflow_support/flavors/mlflow_gluon.py
splicemachine/mlflow_support/flavors/mlflow_h2o.py
splicemachine/mlflow_support/flavors/mlflow_keras.py
splicemachine/mlflow_support/flavors/mlflow_lightgbm.py
splicemachine/mlflow_support/flavors/mlflow_mleap.py
splicemachine/mlflow_support/flavors/mlflow_onnx.py
splicemachine/mlflow_support/flavors/mlflow_pyfunc.py
splicemachine/mlflow_support/flavors/mlflow_pytorch.py
splicemachine/mlflow_support/flavors/mlflow_sklearn.py
splicemachine/mlflow_support/flavors/mlflow_spacy.py
splicemachine/mlflow_support/flavors/mlflow_spark.py
splicemachine/mlflow_support/flavors/mlflow_statsmodels.py
splicemachine/mlflow_support/flavors/mlflow_tensorflow.py
splicemachine/mlflow_support/flavors/mlflow_xgboost.py
splicemachine/spark/__init__.py
