Metadata-Version: 2.1
Name: splicemachine
Version: 2.9.0.dev1
Summary: This package contains all of the classes and functions you need to interact with Splice Machine's scale out, real-time, ACID compliant ML Engine. It contains several machine learning utilities for use with Apache Spark, a managed MLFlow client and a Managed Feature Store client.
Home-page: https://github.com/splicemachine/pysplice/
Author: Splice Machine, Inc.
Author-email: abaveja@splicemachine.com
License: Apache License, Version 2.0
Platform: UNKNOWN
Provides-Extra: notebook
Provides-Extra: stats
Provides-Extra: ml
Provides-Extra: all
